cfndeployer.py
cfn/__init__.py
cfn/cfn.py
cfn_deployer-0.5.dist-info/METADATA
cfn_deployer-0.5.dist-info/RECORD
cfn_deployer-0.5.dist-info/WHEEL
cfn_deployer-0.5.dist-info/entry_points.txt
cfn_deployer-0.5.dist-info/top_level.txt
