Metadata-Version: 2.1
Name: cfn-deployer
Version: 0.5
Summary: UNKNOWN
Home-page: UNKNOWN
Author: Cory Kitchens
Author-email: corykitchens@gmail.com
License: UNKNOWN
Platform: UNKNOWN
Requires-Dist: Click
Requires-Dist: boto3
